COSCST/SAE.py
COSCST/__init__.py
COSCST/coscst.py
COSCST/network.py
COSCST-0.1.dist-info/METADATA
COSCST-0.1.dist-info/WHEEL
COSCST-0.1.dist-info/top_level.txt
COSCST-0.1.dist-info/RECORD
